{
  "db_name": "PostgreSQL",
  "query": "SELECT * FROM card_block_comments WHERE card_id = $1 ORDER BY created_at ASC",
  "describe": {
    "columns": [
      {
        "ordinal": 0,
        "name": "id",
        "type_info": "Uuid"
      },
      {
        "ordinal": 1,
        "name": "card_id",
        "type_info": "Uuid"
      },
      {
        "ordinal": 2,
        "name": "user_id",
        "type_info": "Uuid"
      },
      {
        "ordinal": 3,
        "name": "content",
        "type_info": "Text"
      },
      {
        "ordinal": 4,
        "name": "created_at",
        "type_info": "Timestamptz"
      },
      {
        "ordinal": 5,
        "name": "updated_at",
        "type_info": "Timestamptz"
      }
    ],
    "parameters": {
      "Left": [
        "Uuid"
      ]
    },
    "nullable": [
      false,
      false,
      false,
      false,
      false,
      false
    ]
  },
  "hash": "375c5987761d31880867e3c8aab2a6f4a99b9a64b843bef10eb19cf6e01c00ad"
}
